postcode_validator/__init__.py
postcode_validator/Exceptions/__init__.py
postcode_validator/Exceptions/exceptions.py
postcode_validator/uk/__init__.py
postcode_validator/uk/uk_postcode_regex.py
postcode_validator/uk/uk_postcode_validator.py
postcode_validator-0.0.4.dist-info/LICENSE
postcode_validator-0.0.4.dist-info/METADATA
postcode_validator-0.0.4.dist-info/WHEEL
postcode_validator-0.0.4.dist-info/top_level.txt
postcode_validator-0.0.4.dist-info/RECORD
