Metadata-Version: 2.1
Name: postcode-validator
Version: 0.0.4
Summary: Postcode Validator Library
Home-page: https://github.com/GouthamSiddhaarth/postcode_validator
Author: Goutham Siddhaarth M.S.K
Author-email: mskgouthamsiddhaarth@gmail.com
License: MIT
Platform: UNKNOWN
Classifier: License :: OSI Approved :: MIT License
Classifier: Programming Language :: Python :: 3.8
License-File: LICENSE
